lithium_kernel/__init__.py
lithium_kernel/__main__.py
lithium_kernel/install.py
lithium_kernel/kernel.py
lithium_kernel-0.2.0.dist-info/WHEEL
lithium_kernel-0.2.0.dist-info/METADATA
lithium_kernel-0.2.0.dist-info/RECORD
